bandown/Bandown.py
bandown/__init__.py
bandown/__main__.py
bandown/options.py
bandown-0.0.1.data/scripts/bandown
bandown-0.0.1.dist-info/METADATA
bandown-0.0.1.dist-info/RECORD
bandown-0.0.1.dist-info/WHEEL
bandown-0.0.1.dist-info/top_level.txt
